slidie/__init__.py
slidie/builds.py
slidie/embed_thumbnails.py
slidie/ffmpeg.py
slidie/file_numbering.py
slidie/inkscape.py
slidie/links.py
slidie/magic.py
slidie/metadata.py
slidie/speaker_notes.py
slidie/svg_utils.py
slidie/text_to_selectable_paths.py
slidie/video.py
slidie/xml_namespaces.py
slidie/render_pdf/__init__.py
slidie/render_pdf/pdf.py
slidie/render_png/__init__.py
slidie/render_xhtml/__init__.py
slidie/render_xhtml/base.css
slidie/render_xhtml/base.xhtml
slidie/render_xhtml/browser_magic.py
slidie/render_xhtml/common.css
slidie/render_xhtml/presenter_view.css
slidie/render_xhtml/presenter_view.xhtml
slidie/render_xhtml/template.py
slidie/render_xhtml/viewer/eslint.config.js
slidie/render_xhtml/viewer/index.js
slidie/render_xhtml/viewer/index.js.map
slidie/render_xhtml/viewer/node_modules/flatted/python/flatted.py
slidie/render_xhtml/viewer/node_modules/flatted/python/test.py
slidie/scripts/__init__.py
slidie/scripts/exception_formatting.py
slidie/scripts/placeholders.py
slidie/scripts/slidie_cmd.py
slidie/scripts/slidie_mv_cmd.py
slidie/scripts/slidie_video_stills_cmd.py
slidie-0.1.1.dist-info/licenses/LICENCE
slidie-0.1.1.dist-info/METADATA
slidie-0.1.1.dist-info/WHEEL
slidie-0.1.1.dist-info/entry_points.txt
slidie-0.1.1.dist-info/top_level.txt
slidie-0.1.1.dist-info/RECORD
