Metadata-Version: 2.4
Name: slidie
Version: 0.1.1
Summary: An Inkscape-centered slide preparation tool
License:                     GNU GENERAL PUBLIC LICENSE
License-File: LICENCE
Requires-Dist: pikepdf
Dynamic: license-file
